main.py
py_mini_racer/__init__.py
py_mini_racer/armlibmini_racer.dylib
py_mini_racer/armlibmini_racer.glibc.so
py_mini_racer/py_mini_racer.py
akracer-0.0.12.dist-info/METADATA
akracer-0.0.12.dist-info/WHEEL
akracer-0.0.12.dist-info/RECORD
